ordlookup/__init__.py
ordlookup/oleaut32.py
ordlookup/ws2_32.py
pefilenew/__init__.py
pefilenew/pefile.py
pefilenew/peutils.py
pefilenew-2.2.dist-info/DESCRIPTION.rst
pefilenew-2.2.dist-info/METADATA
pefilenew-2.2.dist-info/RECORD
pefilenew-2.2.dist-info/WHEEL
pefilenew-2.2.dist-info/metadata.json
pefilenew-2.2.dist-info/top_level.txt
